camunda_adapter/__init__.py
camunda_adapter/adapters.py
camunda_adapter/config.py
camunda_adapter/const.py
camunda_adapter/utils.py
camunda_adapter/domain/__init__.py
camunda_adapter/domain/model.py
camunda_adapter-1.1.0.dist-info/LICENSE
camunda_adapter-1.1.0.dist-info/METADATA
camunda_adapter-1.1.0.dist-info/WHEEL
camunda_adapter-1.1.0.dist-info/dependency_links.txt
camunda_adapter-1.1.0.dist-info/top_level.txt
camunda_adapter-1.1.0.dist-info/RECORD
