Metadata-Version: 2.1
Name: camunda-adapter
Version: 1.1.0
Summary: Адаптер для BPMN-движка Camunda
Home-page: https://stash.bars-open.ru/projects/M3/repos/camunda-adapter
Author: BARS Group
Author-email: bars@bars-open.ru
License: MIT
Classifier: Intended Audience :: Developers
Classifier: Environment :: Web Environment
Classifier: Natural Language :: Russian
Classifier: Operating System :: OS Independent
Classifier: Programming Language :: Python
Classifier: Programming Language :: Python :: 3.7
Classifier: Programming Language :: Python :: 3.8
Classifier: Programming Language :: Python :: 3.9
Classifier: Programming Language :: Python :: 3.10
Classifier: Programming Language :: Python :: 3.11
Classifier: Development Status :: 5 - Production/Stable
Requires-Python: >=3.7
License-File: LICENSE
Requires-Dist: pydantic
Requires-Dist: requests
